korrektor/__init__.py
korrektor/__version__.py
korrektor/api.py
korrektor/core.py
korrektor/exceptions.py
korrektor/models.py
korrektor/utils.py
korrektor_uz_async-1.0.0.dist-info/LICENSE
korrektor_uz_async-1.0.0.dist-info/METADATA
korrektor_uz_async-1.0.0.dist-info/WHEEL
korrektor_uz_async-1.0.0.dist-info/top_level.txt
korrektor_uz_async-1.0.0.dist-info/RECORD
