Metadata-Version: 2.1
Name: korrektor-uz-async
Version: 1.0.0
Summary: async Python wrapper for the https://korrektor.uz/api
Author-email: Qurbonov Asadbek <qurbonovasadbek@gmail.com>
License: MIT License        
Project-URL: Homepage, https://github.com/advenn/korrektor_uz_async
Project-URL: Bug Tracker, https://github.com/advenn/korrekor_uz_async/issues
Project-URL: Documentation, https://korrektor.uz/api
Classifier: Programming Language :: Python :: 3
Classifier: License :: OSI Approved :: MIT License
Classifier: Operating System :: OS Independent
Requires-Python: >=3.8
License-File: LICENSE
Requires-Dist: aiohttp
Requires-Dist: aiofiles
Requires-Dist: pydantic
